MANIFEST.in
README.md
requirements.txt
setup.py
rb/__init__.py
rb/cna/__init__.py
rb/cna/cna_graph.py
rb/cna/edge_type.py
rb/cna/overlap_type.py
rb/complexity/__init__.py
rb/complexity/complexity_index.py
rb/complexity/index_category.py
rb/complexity/measure_function.py
rb/complexity/cohesion/__init__.py
rb/complexity/cohesion/adj_cohesion.py
rb/complexity/cohesion/adj_ext_cohesion.py
rb/complexity/cohesion/factory.py
rb/complexity/cohesion/intra_cohesion.py
rb/complexity/cohesion/mid_end_cohesion.py
rb/complexity/cohesion/start_end_cohesion.py
rb/complexity/cohesion/start_mid_cohesion.py
rb/complexity/cohesion/trans_cohesion.py
rb/complexity/discourse/__init__.py
rb/complexity/discourse/conn_type_enum.py
rb/complexity/discourse/connectors.py
rb/complexity/discourse/factory.py
rb/complexity/morphology/__init__.py
rb/complexity/morphology/factory.py
rb/complexity/morphology/pos_main.py
rb/complexity/morphology/pron.py
rb/complexity/morphology/pron_type_enum.py
rb/complexity/morphology/unq_pos_main.py
rb/complexity/rhythm/__init__.py
rb/complexity/rhythm/dictionary_utils.py
rb/complexity/rhythm/factory.py
rb/complexity/rhythm/no_alliterations.py
rb/complexity/rhythm/no_assonances.py
rb/complexity/rhythm/no_stressed_syllables.py
rb/complexity/rhythm/no_syllables.py
rb/complexity/rhythm/rhythm_utils.py
rb/complexity/rhythm/rhythmic_coefficient.py
rb/complexity/rhythm/rhythmic_diameter.py
rb/complexity/rhythm/rhythmic_index.py
rb/complexity/rhythm/syllab.py
rb/complexity/rhythm/syllabified_dict.py
rb/complexity/rhythm/usage.py
rb/complexity/surface/__init__.py
rb/complexity/surface/ch_entropy.py
rb/complexity/surface/ch_ngram_entropy.py
rb/complexity/surface/factory.py
rb/complexity/surface/no_cacophonies.py
rb/complexity/surface/no_commas.py
rb/complexity/surface/no_common_errors.py
rb/complexity/surface/no_punctuations.py
rb/complexity/surface/no_sentences.py
rb/complexity/surface/no_unq_words.py
rb/complexity/surface/no_words.py
rb/complexity/surface/wd_entropy.py
rbpy_rb_german.egg-info/PKG-INFO
rbpy_rb_german.egg-info/SOURCES.txt
rbpy_rb_german.egg-info/dependency_links.txt
rbpy_rb_german.egg-info/requires.txt
rbpy_rb_german.egg-info/top_level.txt