Metadata-Version: 2.1
Name: rbpy-rb-german
Version: 0.0.9
Summary: German version of ReaderBench library written in python
Home-page: https://git.readerbench.com/ReaderBench/Readerbench-python
Author: Karl Zeufack
Author-email: karl.zeufack@rwth-aachen.de
License: UNKNOWN
Platform: UNKNOWN
Classifier: Programming Language :: Python :: 3
Classifier: License :: OSI Approved :: Apache Software License
Classifier: Operating System :: OS Independent
Requires-Python: >=3.6,<3.9
